[
  {
    "question": "Which player did Chelsea sack after he failed a drugs test?",
    "answer": "Adrian Mutu.",
    "ground_truth": {
      "article_id": 0,
      "chunk_id": 0
    }
  },
  {
    "question": "What did Adrian Mutu test positive for?",
    "answer": "A banned substance.",
    "ground_truth": {
      "article_id": 0,
      "chunk_id": 0
    }
  },
  {
    "question": "What policy toward drugs did Chelsea say it had?",
    "answer": "A zero tolerance policy towards drugs.",
    "ground_truth": {
      "article_id": 0,
      "chunk_id": 0
    }
  },
  {
    "question": "What policy toward drugs did Chelsea say it had?",
    "answer": "A zero tolerance policy towards drugs.",
    "ground_truth": {
      "article_id": 0,
      "chunk_id": 1
    }
  }
]